Metadata-Version: 1.1
Name: dEploid
Version: 0.6.0a2
Summary: dEploid CPP module
Home-page: https://github.com/DEploid-dev/DEploid-py
Author: Joe Zhu
Author-email: joe.zhu@bdi.ox.ac.uk
License: GNU GPLv3+
Keywords: deconvolution,mixed infection
Platform: POSIX
Classifier: Programming Language :: C++
Classifier: Programming Language :: C
Classifier: Programming Language :: Python
Classifier: Programming Language :: Python :: 3
Classifier: Programming Language :: Python :: 3.3
Classifier: Programming Language :: Python :: 3.4
Classifier: Programming Language :: Python :: 3.5
Classifier: Programming Language :: Python :: 3.6
Classifier: Development Status :: 2 - Pre-Alpha
Classifier: Environment :: Other Environment
Classifier: Intended Audience :: Science/Research
Classifier: License :: OSI Approved :: GNU General Public License v3 or later (GPLv3+)
Classifier: Operating System :: POSIX
Classifier: Operating System :: MacOS :: MacOS X
Classifier: Topic :: Scientific/Engineering
Classifier: Topic :: Scientific/Engineering :: Bio-Informatics
